ejercicio_8/verilog/trigger_enable_logic/src/pulse.v
`timescale 1ns / 1ps

// generates a pulse given a signal that changed it's state
module pulse(SR_ECHO, RESET, MEAS_EN);

	input SR_ECHO;
	input RESET;
	wire partial;

	output MEAS_EN;
	assign #1 partial = SR_ECHO || RESET;
	
	assign #1 p1 = !partial;
	assign #1 p2 = !p1;
	assign #1 p3 = !p2;
	assign #1 p4 = !(p3 || partial);
	assign #1 p5 = !p4;
	assign #1 MEAS_EN = !p5;
endmodule

ejercicio_8/verilog/trigger_enable_logic/src/trigger_enable.v
`timescale 1ns / 1ps

module trigger_enable_logic(
	TRIG_EN,
	TRIG,
	ECHO,
	SR_TRIG,
	MEAS_RESET,
	MEAS_READY);
	
	input TRIG_EN;
	input TRIG;
	
	input ECHO;

	output SR_TRIG;
	output MEAS_READY;
	output MEAS_RESET;

	reg Q; // flip flop register
	wire Qn;

	wire CLK;
	wire MEAS_EN;

	pulse my_meas(ECHO,1'b0,MEAS_EN);	
	assign Qn = !Q;

	assign SR_TRIG = TRIG_EN && TRIG && !Q;
	assign MEAS_READY = !Q;
	
	assign CLK = TRIG && !Q;

	always @MEAS_EN
	begin
		if (MEAS_EN)
			assign Q = 0;
		else
			deassign Q;
	end
	
	always @(negedge CLK) begin
		Q <= !Q;
	end
	

endmodule

ejercicio_8/verilog/trigger_enable_logic/src/trigger_enable_test.v
`timescale 1ns / 1ps

module simple_tb;

   // initial values
   reg TRIGGER_EN;
   reg TRIG;
   reg ECHO;

   wire SR_TRIG;
   wire MEAS_READY;
   wire MEAS_RESET;

   integer it1;

   initial
     begin
        // vcd dump
        $dumpfile("trigger_enable.vcd");
        // the variable 's' is what GTKWave will label the graphs with
        $dumpvars(0, s);
        //$monitor("SR_ECHO is %b, ", SR_ECHO);
	
	#0 TRIGGER_EN = 1;
	#0 ECHO = 0;

	for (it1 = 0;it1 <= 1000;it1=it1+1) begin
		if (it1 % 10 == 5) begin        	
			#1 TRIG = 1;
		end
		if (it1 % 10 == 0) begin
			#1 TRIG = 0;
		end
		if (it1 % 50 == 25) begin
			#0  ECHO = 0;
		end
		if (it1 % 50 == 0) begin
			#0 ECHO = 1;
		end

		#1 TRIG = 0;

        end        
	
	$finish;
        
     end

   // stap of module
   trigger_enable_logic s(TRIGGER_EN, TRIG, ECHO, SR_TRIG, MEAS_RESET, MEAS_READY);
endmodule

ejercicio_8/verilog/trigger_enable_logic/trigger_enable.vcd
$date
	Wed Oct 17 13:31:24 2018
$end
$version
	Icarus Verilog
$end
$timescale
	1ps
$end
$scope module simple_tb $end
$scope module s $end
$var wire 1 ! CLK $end
$var wire 1 " ECHO $end
$var wire 1 # MEAS_RESET $end
$var wire 1 $ SR_TRIG $end
$var wire 1 % TRIG $end
$var wire 1 & TRIG_EN $end
$var wire 1 ' Qn $end
$var wire 1 ( MEAS_READY $end
$var wire 1 ) MEAS_EN $end
$var reg 1 * Q $end
$scope module my_meas $end
$var wire 1 + RESET $end
$var wire 1 " SR_ECHO $end
$var wire 1 , partial $end
$var wire 1 - p5 $end
$var wire 1 . p4 $end
$var wire 1 / p3 $end
$var wire 1 0 p2 $end
$var wire 1 1 p1 $end
$var wire 1 ) MEAS_EN $end
$upscope $end
$upscope $end
$upscope $end
$enddefinitions $end
#0
$dumpvars
x1
x0
x/
x.
x-
x,
0+
x*
x)
x(
x'
1&
x%
x$
z#
0"
x!
$end
#1000
0$
1"
0!
0,
0%
#2000
1,
11
#3000
0.
01
00
#4000
1-
10
1/
#5000
0)
0/
#7000
x$
x!
1%
#8000
0$
0!
0%
#19000
x$
x!
1%
#20000
0$
0!
0%
#31000
x$
0"
x!
1%
#32000
0$
0!
0,
0%
#33000
1.
11
#34000
0-
00
#35000
1'
1(
0*
1)
1/
#36000
0.
#37000
1-
#38000
0)
#43000
1$
1!
1%
#44000
0'
0(
1*
0$
0!
0%
#55000
1%
#56000
0%
#61000
1"
#62000
1,
#63000
01
#64000
10
#65000
0/
#67000
1%
#68000
0%
#79000
1%
#80000
0%
#91000
0"
1%
#92000
0,
0%
#93000
1.
11
#94000
0-
00
#95000
1'
1(
0*
1)
1/
#96000
0.
#97000
1-
#98000
0)
#103000
1$
1!
1%
#104000
0'
0(
1*
0$
0!
0%
#115000
1%
#116000
0%
#121000
1"
#122000
1,
#123000
01
#124000
10
#125000
0/
#127000
1%
#128000
0%
#139000
1%
#140000
0%
#151000
0"
1%
#152000
0,
0%
#153000
1.
11
#154000
0-
00
#155000
1'
1(
0*
1)
1/
#156000
0.
#157000
1-
#158000
0)
#163000
1$
1!
1%
#164000
0'
0(
1*
0$
0!
0%
#175000
1%
#176000
0%
#181000
1"
#182000
1,
#183000
01
#184000
10
#185000
0/
#187000
1%
#188000
0%
#199000
1%
#200000
0%
#211000
0"
1%
#212000
0,
0%
#213000
1.
11
#214000
0-
00
#215000
1'
1(
0*
1)
1/
#216000
0.
#217000
1-
#218000
0)
#223000
1$
1!
1%
#224000
0'
0(
1*
0$
0!
0%
#235000
1%
#236000
0%
#241000
1"
#242000
1,
#243000
01
#244000
10
#245000
0/
#247000
1%
#248000
0%
#259000
1%
#260000
0%
#271000
0"
1%
#272000
0,
0%
#273000
1.
11
#274000
0-
00
#275000
1'
1(
0*
1)
1/
#276000
0.
#277000
1-
#278000
0)
#283000
1$
1!
1%
#284000
0'
0(
1*
0$
0!
0%
#295000
1%
#296000
0%
#301000
1"
#302000
1,
#303000
01
#304000
10
#305000
0/
#307000
1%
#308000
0%
#319000
1%
#320000
0%
#331000
0"
1%
#332000
0,
0%
#333000
1.
11
#334000
0-
00
#335000
1'
1(
0*
1)
1/
#336000
0.
#337000
1-
#338000
0)
#343000
1$
1!
1%
#344000
0'
0(
1*
0$
0!
0%
#355000
1%
#356000
0%
#361000
1"
#362000
1,
#363000
01
#364000
10
#365000
0/
#367000
1%
#368000
0%
#379000
1%
#380000
0%
#391000
0"
1%
#392000
0,
0%
#393000
1.
11
#394000
0-
00
#395000
1'
1(
0*
1)
1/
#396000
0.
#397000
1-
#398000
0)
#403000
1$
1!
1%
#404000
0'
0(
1*
0$
0!
0%
#415000
1%
#416000
0%
#421000
1"
#422000
1,
#423000
01
#424000
10
#425000
0/
#427000
1%
#428000
0%
#439000
1%
#440000
0%
#451000
0"
1%
#452000
0,
0%
#453000
1.
11
#454000
0-
00
#455000
1'
1(
0*
1)
1/
#456000
0.
#457000
1-
#458000
0)
#463000
1$
1!
1%
#464000
0'
0(
1*
0$
0!
0%
#475000
1%
#476000
0%
#481000
1"
#482000
1,
#483000
01
#484000
10
#485000
0/
#487000
1%
#488000
0%
#499000
1%
#500000
0%
#511000
0"
1%
#512000
0,
0%
#513000
1.
11
#514000
0-
00
#515000
1'
1(
0*
1)
1/
#516000
0.
#517000
1-
#518000
0)
#523000
1$
1!
1%
#524000
0'
0(
1*
0$
0!
0%
#535000
1%
#536000
0%
#541000
1"
#542000
1,
#543000
01
#544000
10
#545000
0/
#547000
1%
#548000
0%
#559000
1%
#560000
0%
#571000
0"
1%
#572000
0,
0%
#573000
1.
11
#574000
0-
00
#575000
1'
1(
0*
1)
1/
#576000
0.
#577000
1-
#578000
0)
#583000
1$
1!
1%
#584000
0'
0(
1*
0$
0!
0%
#595000
1%
#596000
0%
#601000
1"
#602000
1,
#603000
01
#604000
10
#605000
0/
#607000
1%
#608000
0%
#619000
1%
#620000
0%
#631000
0"
1%
#632000
0,
0%
#633000
1.
11
#634000
0-
00
#635000
1'
1(
0*
1)
1/
#636000
0.
#637000
1-
#638000
0)
#643000
1$
1!
1%
#644000
0'
0(
1*
0$
0!
0%
#655000
1%
#656000
0%
#661000
1"
#662000
1,
#663000
01
#664000
10
#665000
0/
#667000
1%
#668000
0%
#679000
1%
#680000
0%
#691000
0"
1%
#692000
0,
0%
#693000
1.
11
#694000
0-
00
#695000
1'
1(
0*
1)
1/
#696000
0.
#697000
1-
#698000
0)
#703000
1$
1!
1%
#704000
0'
0(
1*
0$
0!
0%
#715000
1%
#716000
0%
#721000
1"
#722000
1,
#723000
01
#724000
10
#725000
0/
#727000
1%
#728000
0%
#739000
1%
#740000
0%
#751000
0"
1%
#752000
0,
0%
#753000
1.
11
#754000
0-
00
#755000
1'
1(
0*
1)
1/
#756000
0.
#757000
1-
#758000
0)
#763000
1$
1!
1%
#764000
0'
0(
1*
0$
0!
0%
#775000
1%
#776000
0%
#781000
1"
#782000
1,
#783000
01
#784000
10
#785000
0/
#787000
1%
#788000
0%
#799000
1%
#800000
0%
#811000
0"
1%
#812000
0,
0%
#813000
1.
11
#814000
0-
00
#815000
1'
1(
0*
1)
1/
#816000
0.
#817000
1-
#818000
0)
#823000
1$
1!
1%
#824000
0'
0(
1*
0$
0!
0%
#835000
1%
#836000
0%
#841000
1"
#842000
1,
#843000
01
#844000
10
#845000
0/
#847000
1%
#848000
0%
#859000
1%
#860000
0%
#871000
0"
1%
#872000
0,
0%
#873000
1.
11
#874000
0-
00
#875000
1'
1(
0*
1)
1/
#876000
0.
#877000
1-
#878000
0)
#883000
1$
1!
1%
#884000
0'
0(
1*
0$
0!
0%
#895000
1%
#896000
0%
#901000
1"
#902000
1,
#903000
01
#904000
10
#905000
0/
#907000
1%
#908000
0%
#919000
1%
#920000
0%
#931000
0"
1%
#932000
0,
0%
#933000
1.
11
#934000
0-
00
#935000
1'
1(
0*
1)
1/
#936000
0.
#937000
1-
#938000
0)
#943000
1$
1!
1%
#944000
0'
0(
1*
0$
0!
0%
#955000
1%
#956000
0%
#961000
1"
#962000
1,
#963000
01
#964000
10
#965000
0/
#967000
1%
#968000
0%
#979000
1%
#980000
0%
#991000
0"
1%
#992000
0,
0%
#993000
1.
11
#994000
0-
00
#995000
1'
1(
0*
1)
1/
#996000
0.
#997000
1-
#998000
0)
#1003000
1$
1!
1%
#1004000
0'
0(
1*
0$
0!
0%
#1015000
1%
#1016000
0%
#1021000
1"
#1022000
1,
#1023000
01
#1024000
10
#1025000
0/
#1027000
1%
#1028000
0%
#1039000
1%
#1040000
0%
#1051000
0"
1%
#1052000
0,
0%
#1053000
1.
11
#1054000
0-
00
#1055000
1'
1(
0*
1)
1/
#1056000
0.
#1057000
1-
#1058000
0)
#1063000
1$
1!
1%
#1064000
0'
0(
1*
0$
0!
0%
#1075000
1%
#1076000
0%
#1081000
1"
#1082000
1,
#1083000
01
#1084000
10
#1085000
0/
#1087000
1%
#1088000
0%
#1099000
1%
#1100000
0%
#1111000
0"
1%
#1112000
0,
0%
#1113000
1.
11
#1114000
0-
00
#1115000
1'
1(
0*
1)
1/
#1116000
0.
#1117000
1-
#1118000
0)
#1123000
1$
1!
1%
#1124000
0'
0(
1*
0$
0!
0%
#1135000
1%
#1136000
0%
#1141000
1"
#1142000
1,
#1143000
01
#1144000
10
#1145000
0/
#1147000
1%
#1148000
0%
#1159000
1%
#1160000
0%
#1171000
0"
1%
#1172000
0,
0%
#1173000
1.
11
#1174000
0-
00
#1175000
1'
1(
0*
1)
1/
#1176000
0.
#1177000
1-
#1178000
0)
#1183000
1$
1!
1%
#1184000
0'
0(
1*
0$
0!
0%
#1195000
1%
#1196000
0%
#1201000
1"
#1202000
1,
