ejercicio_8/verilog/counter/src/bin2bcd.v
`timescale 1ns / 1ps

// very standard Verilog module
module bcd_counter(
	CLK,
	RST,
	CRY_OUT,
	OUT
	);
	
	input CLK;
	input RST;
	
	output CRY_OUT;
	output DIGITS;

	output reg [3:0]OUT;
	
endmodule

module bin_to_hex(
	NUMBER,
	DIGITS);
	input [3:0]NUMBER;
	output [7:0]DIGITS;
	reg [7:0] data [0:9]; // a b c d e f g
	
	initial begin
		data[0] <= 7'b1111110;
		data[1] <= 7'b0110000;
		data[2] <= 7'b1101101;
		data[3] <= 7'b1111011;
		data[4] <= 7'b0110011;
		data[5] <= 7'b1010011;
		data[6] <= 7'b1011111;
		data[7] <= 7'b1110011;
		data[8] <= 7'b1111111;
		data[9] <= 7'b1110011;
	end
	
	assign DIGITS = data[NUMBER];

endmodule

ejercicio_8/verilog/counter/src/bin2bcd_test.v

module simple_tb;

   // initial values

   integer digit;
   reg [3:0]NUMBER;
   wire [7:0]DIGITS;

   initial
     begin
        // vcd dump
        $dumpfile("bin2bcd.vcd");
        // the variable 's' is what GTKWave will label the graphs with
        $dumpvars(0, s);
        //$monitor("SR_ECHO is %b, ", SR_ECHO);
	for (digit = 0;digit <= 9;digit = digit + 1) begin
		#1 NUMBER = digit;
	end
        // setting each elements values at each time interval, must finish with $finish
	
        #495 $finish;
     end

   // stap of module
   bin_to_hex s(NUMBER, DIGITS);
endmodule

ejercicio_8/verilog/bin2bcd/bin2bcd.vcd
$date
	Wed Oct 17 20:48:55 2018
$end
$version
	Icarus Verilog
$end
$timescale
	1ps
$end
$scope module simple_tb $end
$scope module s $end
$var wire 8 ! DIGITS [7:0] $end
$var wire 4 " NUMBER [3:0] $end
$upscope $end
$upscope $end
$enddefinitions $end
#0
$dumpvars
bx "
bx !
$end
#1000000000000
b1111110 !
b0 "
#2000000000000
b110000 !
b1 "
#3000000000000
b1101101 !
b10 "
#4000000000000
b1111011 !
b11 "
#5000000000000
b110011 !
b100 "
#6000000000000
b1010011 !
b101 "
#7000000000000
b1011111 !
b110 "
#8000000000000
b1110011 !
b111 "
#9000000000000
b1111111 !
b1000 "
#10000000000000
b1110011 !
b1001 "
