ejercicio_8/verilog/pulse/src/pulse.v
`timescale 1ns / 1ps

// very standard Verilog module
module pulse(SR_ECHO, RESET, MEAS_EN);

	input SR_ECHO;
	input RESET;
	wire partial;

	output MEAS_EN;
	assign #1 partial = SR_ECHO || RESET;
	
	assign #1 p1 = !partial;
	assign #1 p2 = !p1;
	assign #1 p3 = !p2;
	assign #1 p4 = !(p3 || partial);
	assign #1 p5 = !p4;
	assign #1 MEAS_EN = !p5;
endmodule

ejercicio_8/verilog/pulse/src/pulse_test.v
`timescale 1ns / 1ps

module simple_tb;

   // initial values
   reg SR_ECHO;
   reg RESET;
   wire MEAS_EN;

   initial
     begin
        // vcd dump
        $dumpfile("pulse.vcd");
        // the variable 's' is what GTKWave will label the graphs with
        $dumpvars(0, s);
        //$monitor("SR_ECHO is %b, ", SR_ECHO);

        // setting each elements values at each time interval, must finish with $finish
	#0 RESET = 0;
	#0 SR_ECHO = 0;

        #500 SR_ECHO = 1;
	#30 SR_ECHO = 0;
        
	//#50 A = 4'b0000;
        #495 $finish;
     end

   // stap of module
   pulse s(SR_ECHO, RESET, MEAS_EN);
endmodule

ejercicio_8/verilog/pulse/pulse.vcd
$date
	Wed Oct 17 20:49:06 2018
$end
$version
	Icarus Verilog
$end
$timescale
	1ps
$end
$scope module simple_tb $end
$scope module s $end
$var wire 1 ! RESET $end
$var wire 1 " SR_ECHO $end
$var wire 1 # partial $end
$var wire 1 $ p5 $end
$var wire 1 % p4 $end
$var wire 1 & p3 $end
$var wire 1 ' p2 $end
$var wire 1 ( p1 $end
$var wire 1 ) MEAS_EN $end
$upscope $end
$upscope $end
$enddefinitions $end
#0
$dumpvars
x)
x(
x'
x&
x%
x$
x#
0"
0!
$end
#1000
0#
#2000
1(
#3000
0'
#4000
1&
#5000
0%
#6000
1$
#7000
0)
#500000
1"
#501000
1#
#502000
0(
#503000
1'
#504000
0&
#530000
0"
#531000
0#
#532000
1%
1(
#533000
0$
0'
#534000
1)
1&
#535000
0%
#536000
1$
#537000
0)
